MANIFEST.in
README.rst
requirements.txt
setup.cfg
setup.py
webaio/__init__.py
webaio/decorators.py
webaio/exceptions.py
webaio/middlewares.py
webaio/patterns.py
webaio/routers.py
webaio/status.py
webaio/viewsets.py
webaio.egg-info/PKG-INFO
webaio.egg-info/SOURCES.txt
webaio.egg-info/dependency_links.txt
webaio.egg-info/not-zip-safe
webaio.egg-info/requires.txt
webaio.egg-info/top_level.txt
webaio/scripts/__init__.py
webaio/scripts/webaio-create-app.py
webaio/scripts/webaio-create-project.py
webaio/tests/__init__.py
webaio/tests/test_patterns.py
webaio/tests/test_routers.py